setup.cfg
setup.py
sr_auth/__init__.py
sr_auth/api_client.py
sr_auth/configuration.py
sr_auth/rest.py
sr_auth.egg-info/PKG-INFO
sr_auth.egg-info/SOURCES.txt
sr_auth.egg-info/dependency_links.txt
sr_auth.egg-info/requires.txt
sr_auth.egg-info/top_level.txt
sr_auth/apis/__init__.py
sr_auth/apis/default_api.py
sr_auth/models/__init__.py
sr_auth/models/credential.py
sr_auth/models/error.py
sr_auth/models/response.py
test/test_credential.py
test/test_default_api.py
test/test_error.py
test/test_response.py