Metadata-Version: 1.0
Name: sr-auth
Version: 1.0.1
Summary: SR-Auth API
Home-page: https://src-code.simons-rock.edu/git/infra/sr-auth
Author: Dennis Chen
Author-email: barracks510@gmail.com 
License: UNKNOWN
Keywords: Swagger,SR-Auth API
Platform: UNKNOWN
